{
  "gitSyncId": "664ce1518d7e96499702e486_9c72ffdc-4a52-45cc-8ab0-63f373576f8a",
  "id": "CadastroFuncionario_cadastrarFuncionario.cadastrarFuncionario",
  "pluginId": "js-plugin",
  "pluginType": "JS",
  "unpublishedAction": {
    "actionConfiguration": {
      "encodeParamsToggle": true,
      "jsArguments": [],
      "paginationType": "NONE",
      "timeoutInMillisecond": 10000
    },
    "collectionId": "CadastroFuncionario_cadastrarFuncionario",
    "confirmBeforeExecute": false,
    "datasource": {
      "isAutoGenerated": false,
      "name": "UNUSED_DATASOURCE",
      "pluginId": "js-plugin"
    },
    "dynamicBindingPathList": [
      {
        "key": "body"
      }
    ],
    "executeOnLoad": false,
    "fullyQualifiedName": "cadastrarFuncionario.cadastrarFuncionario",
    "name": "cadastrarFuncionario",
    "pageId": "CadastroFuncionario",
    "userSetOnLoad": false
  }
}