{
  "gitSyncId": "664ce1518d7e96499702e486_0c57b10b-85dc-40f3-aea7-89491e49b300",
  "id": "HomePontista_registrarEntradaSaida.registrarSaida",
  "pluginId": "js-plugin",
  "pluginType": "JS",
  "unpublishedAction": {
    "actionConfiguration": {
      "encodeParamsToggle": true,
      "jsArguments": [],
      "paginationType": "NONE",
      "timeoutInMillisecond": 10000
    },
    "collectionId": "HomePontista_registrarEntradaSaida",
    "confirmBeforeExecute": false,
    "datasource": {
      "isAutoGenerated": false,
      "name": "UNUSED_DATASOURCE",
      "pluginId": "js-plugin"
    },
    "dynamicBindingPathList": [
      {
        "key": "body"
      }
    ],
    "executeOnLoad": false,
    "fullyQualifiedName": "registrarEntradaSaida.registrarSaida",
    "name": "registrarSaida",
    "pageId": "HomePontista",
    "userSetOnLoad": false
  }
}