{
  "gitSyncId": "664ce1518d7e96499702e486_8c108593-5327-416d-a02d-909d15f5dc54",
  "id": "CalendarioSupervisor_DataAtual.getCurrentYear",
  "pluginId": "js-plugin",
  "pluginType": "JS",
  "unpublishedAction": {
    "actionConfiguration": {
      "encodeParamsToggle": true,
      "jsArguments": [],
      "paginationType": "NONE",
      "timeoutInMillisecond": 10000
    },
    "collectionId": "CalendarioSupervisor_DataAtual",
    "confirmBeforeExecute": false,
    "datasource": {
      "isAutoGenerated": false,
      "name": "UNUSED_DATASOURCE",
      "pluginId": "js-plugin"
    },
    "dynamicBindingPathList": [
      {
        "key": "body"
      }
    ],
    "executeOnLoad": false,
    "fullyQualifiedName": "DataAtual.getCurrentYear",
    "name": "getCurrentYear",
    "pageId": "CalendarioSupervisor",
    "userSetOnLoad": false
  }
}