{
  "gitSyncId": "664ce1518d7e96499702e486_df035a1e-cb90-455f-a5de-faabf229be41",
  "id": "Calendario_ Copy_DataAtual.getCurrentYear",
  "pluginId": "js-plugin",
  "pluginType": "JS",
  "unpublishedAction": {
    "actionConfiguration": {
      "encodeParamsToggle": true,
      "jsArguments": [],
      "paginationType": "NONE",
      "timeoutInMillisecond": 10000
    },
    "collectionId": "Calendario_ Copy_DataAtual",
    "confirmBeforeExecute": false,
    "datasource": {
      "isAutoGenerated": false,
      "name": "UNUSED_DATASOURCE",
      "pluginId": "js-plugin"
    },
    "dynamicBindingPathList": [
      {
        "key": "body"
      }
    ],
    "executeOnLoad": false,
    "fullyQualifiedName": "DataAtual.getCurrentYear",
    "name": "getCurrentYear",
    "pageId": "Calendario_ Copy",
    "userSetOnLoad": false
  }
}